pypzbattlesnake/__init__.py
pypzbattlesnake/common.py
pypzbattlesnake/env.py
pypzbattlesnake/renderer.py
pypzbattlesnake/resources/head.svg
pypzbattlesnake/resources/tail.svg
pypzbattlesnake-0.0.3.dist-info/LICENSE
pypzbattlesnake-0.0.3.dist-info/WHEEL
pypzbattlesnake-0.0.3.dist-info/METADATA
pypzbattlesnake-0.0.3.dist-info/RECORD
